pts_eps_psu/__init__.py
pts_eps_psu/eps_mp_psu.py
pts_eps_psu-0.0.3.dist-info/LICENSE.txt
pts_eps_psu-0.0.3.dist-info/METADATA
pts_eps_psu-0.0.3.dist-info/WHEEL
pts_eps_psu-0.0.3.dist-info/top_level.txt
pts_eps_psu-0.0.3.dist-info/RECORD
