Metadata-Version: 2.1
Name: pts-eps-psu
Version: 0.0.3
Summary: EPS/MP-21200 PSU Driver and Diagnostic Package
Home-page: https://gitlab.com/pass-testing-solutions/eps-mp-21200-psu
Author: Pass testing Solutions GmbH
Author-email: shuparna@pass-testing.de
License: MIT
Platform: UNKNOWN
Classifier: License :: OSI Approved :: MIT License
Classifier: Programming Language :: Python :: 3
Classifier: Programming Language :: Python :: 3.9
License-File: LICENSE.txt
Requires-Dist: pyvisa (==1.12.0)
Requires-Dist: pyvisa-py (==0.5.3)
